[
  {
    "title": "Machine Learning A-Z: AI, Python & R",
    "issuer": "Udemy",
    "date": "August 24, 2025",
    "image": "/certifications/udemy-machine-learning-a-z.png",
    "credentialUrl": "https://www.udemy.com/certificate/UC-4dd79e0c-3ad2-4b47-b7da-23639235eca4/"
  },
  {
    "title": "Blue Team Junior Analyst",
    "issuer": "Microsoft",
    "date": "August 01, 2024",
    "image": "/certifications/blue-team.png",
    "credentialUrl": "https://elearning.securityblue.team/home/certificate/171603875"
  },
  {
    "title": "Data Analyst with Python",
    "issuer": "Datacamp",
    "date": "October 22, 2022",
    "image": "/certifications/datacamp-data-analyst.png",
    "credentialUrl": "https://www.datacamp.com/statement-of-accomplishment/track/5f66e7939e826048c35a631930f352aee9a5b1da"
  },
  {
    "title": "Python for Data Science, AI & Development",
    "issuer": "Coursera",
    "date": "June 11, 2023",
    "image": "/certifications/ibm-python-for-data-science.png",
    "credentialUrl": "https://www.coursera.org/account/accomplishments/certificate/V7PQE38FZJ2N"
  }
]
